{"assets":{"D099FE1C947705C8D260EED90B467F68":{"type":"texture","index":18,"assetRequest":{"type":"slide","state":"incoming","slide":"2C21C783-D521-468A-A97D-288E8D4A35C2"},"url":{"web":"assets/D099FE1C947705C8D260EED90B467F68.svg"},"width":1920,"height":1080},"DD24EB82609351303F07EBC8C619EA22":{"type":"texture","index":17,"assetRequest":{"type":"slide","state":"outgoing","slide":"63ADA300-34C0-4DE8-BCAE-3C3E13B79F40"},"url":{"web":"assets/DD24EB82609351303F07EBC8C619EA22.svg"},"width":1920,"height":1080}},"events":[{"effects":[{"beginTime":0,"baseLayer":{"animations":[],"initialState":{"affineTransform":[1,0,0,1,0,0],"masksToBounds":false,"rotation":0,"scale":1,"position":{"pointX":960,"pointY":540},"width":1920,"sublayerTransform":[1,0,0,0,0,1,0,0,0,0,1,0,0,0,0,1],"contentsRect":{"y":0,"x":0,"width":1,"height":1},"opacity":1,"edgeAntialiasingMask":251658240,"height":1080,"hidden":false,"anchorPoint":{"pointX":0.5,"pointY":0.5}},"objectID":"0","layers":[{"animations":[],"initialState":{"affineTransform":[1,0,0,1,0,0],"masksToBounds":false,"rotation":0,"scale":1,"position":{"pointX":960,"pointY":540},"width":1920,"sublayerTransform":[1,0,0,0,0,1,0,0,0,0,1,-0.0003500791246677598,0,0,0,1],"contentsRect":{"y":0,"x":0,"width":1,"height":1},"opacity":1,"edgeAntialiasingMask":251658240,"height":1080,"hidden":false,"anchorPoint":{"pointX":0.5,"pointY":0.5}},"layers":[{"animations":[],"layers":[],"initialState":{"affineTransform":[1,0,0,1,0,0],"masksToBounds":false,"rotation":0,"scale":1,"position":{"pointX":960,"pointY":540},"width":1920,"sublayerTransform":[1,0,0,0,0,1,0,0,0,0,1,0,0,0,0,1],"contentsRect":{"y":0,"x":0,"width":1,"height":1},"opacity":1,"edgeAntialiasingMask":0,"height":1080,"hidden":false,"anchorPoint":{"pointX":0.5,"pointY":0.5}},"texture":"D099FE1C947705C8D260EED90B467F68"},{"animations":[{"timeOffset":0,"from":{"scalar":false},"beginTime":0,"repeatCount":0,"fillMode":"both","property":"hidden","autoreverses":false,"duration":0.01,"to":{"scalar":true}}],"layers":[],"initialState":{"affineTransform":[1,0,0,1,0,0],"masksToBounds":false,"rotation":0,"scale":1,"position":{"pointX":960,"pointY":540},"width":1920,"sublayerTransform":[1,0,0,0,0,1,0,0,0,0,1,0,0,0,0,1],"contentsRect":{"y":0,"x":0,"width":1,"height":1},"opacity":1,"edgeAntialiasingMask":0,"height":1080,"hidden":false,"anchorPoint":{"pointX":0.5,"pointY":0.5}},"texture":"DD24EB82609351303F07EBC8C619EA22"}]}]},"effects":[],"duration":0.01,"type":"transition","name":"none","objectID":"0"}],"automaticPlay":false,"hyperlinks":[{"url":"https://goo.gl/6MjCFN","targetRectangle":{"y":482,"x":282.05,"width":482.7500000000001,"height":58.54965209960938}},{"url":"https://goo.gl/TD7Cax","targetRectangle":{"y":653,"x":282.05,"width":482.45,"height":58.54965209960938}}],"accessibility":[{"text":"Inspirations","targetRectangle":{"y":104,"x":120,"width":488.8000000000001,"height":118.0993041992188}},{"text":"Papers","targetRectangle":{"y":311,"x":170,"width":151.9,"height":58.54965209960938}},{"text":"“Best Practices for Scientific Computing” by Wilson, et al, 2014 (https://goo.gl/6MjCFN)","targetRectangle":{"y":371,"x":270,"width":1370.95,"height":169.5496520996094}},{"text":"“Good enough practices in scientific computing” by Wilson, et al, 2017 (https://goo.gl/TD7Cax)","targetRectangle":{"y":542,"x":270,"width":1530.25,"height":169.5496520996094}},{"text":"People","targetRectangle":{"y":713,"x":170,"width":149.15,"height":109.5496520996094}},{"text":"Hadley Wickham, Jenny Bryan, Karl Broman, Roger Peng, Jeff Leek","targetRectangle":{"y":824,"x":270,"width":1459.2,"height":109.5496520996094}}],"baseLayer":{"animations":[],"initialState":{"affineTransform":[1,0,0,1,0,0],"masksToBounds":false,"rotation":0,"scale":1,"position":{"pointX":960,"pointY":540},"width":1920,"sublayerTransform":[1,0,0,0,0,1,0,0,0,0,1,0,0,0,0,1],"contentsRect":{"y":0,"x":0,"width":1,"height":1},"opacity":1,"edgeAntialiasingMask":251658240,"height":1080,"hidden":false,"anchorPoint":{"pointX":0.5,"pointY":0.5}},"objectID":"0","layers":[{"animations":[],"initialState":{"affineTransform":[1,0,0,1,0,0],"masksToBounds":false,"rotation":0,"scale":1,"position":{"pointX":960,"pointY":540},"width":1920,"sublayerTransform":[1,0,0,0,0,1,0,0,0,0,1,-0.0003500791246677598,0,0,0,1],"contentsRect":{"y":0,"x":0,"width":1,"height":1},"opacity":1,"edgeAntialiasingMask":251658240,"height":1080,"hidden":false,"anchorPoint":{"pointX":0.5,"pointY":0.5}},"layers":[{"animations":[],"layers":[],"initialState":{"affineTransform":[1,0,0,1,0,0],"masksToBounds":false,"rotation":0,"scale":1,"position":{"pointX":960,"pointY":540},"width":1920,"sublayerTransform":[1,0,0,0,0,1,0,0,0,0,1,0,0,0,0,1],"contentsRect":{"y":0,"x":0,"width":1,"height":1},"opacity":1,"edgeAntialiasingMask":0,"height":1080,"hidden":false,"anchorPoint":{"pointX":0.5,"pointY":0.5}},"texture":"DD24EB82609351303F07EBC8C619EA22"}]}]}}]}